full_subtractor/fullsub.v
module full_sub(a,b,c,bor,diff);
input a,b,c;
output bor,diff;
assign bor=(b&&c)||((~a)&&c)||((~a)&&b);
assign diff=a^b^c;
endmodule

full_subtractor/fullsub_t.v
module fullsub_t;
wire bor,diff;
reg a,b,c;
initial
 begin
 $dumpfile("full_subtractor.vcd");
 $dumpvars();    
 end
full_sub h(a,b,c,bor,diff);
 initial 
        begin 
         #0
         a = 0; b = 0; c=0; 
         #5 
         a = 0; b = 0; c=1;
         #10 
         a = 0; b = 1; c=0;
         #15 
         a = 0; b = 1; c=1;
         #20 
         a = 1; b = 0; c=0;
         #25  
         a = 1; b = 0; c=1;
         #30
         a = 1; b = 1; c=0;
         #35
         a = 1; b = 1; c=1;
        end 
endmodule

full_subtractor/full_subtractor.vcd
$date
	Fri May  1 09:53:55 2015
$end
$version
	Icarus Verilog
$end
$timescale
	1s
$end
$scope module fullsub_t $end
$var wire 1 ! bor $end
$var wire 1 " diff $end
$var reg 1 # a $end
$var reg 1 $ b $end
$var reg 1 % c $end
$scope module h $end
$var wire 1 & a $end
$var wire 1 ' b $end
$var wire 1 ! bor $end
$var wire 1 ( c $end
$var wire 1 " diff $end
$upscope $end
$upscope $end
$enddefinitions $end
#0
$dumpvars
0(
0'
0&
0%
0$
0#
0"
0!
$end
#5
1!
1"
1%
1(
#15
0%
0(
1$
1'
#30
0"
1%
1(
#50
0!
1"
0%
0(
0$
0'
1#
1&
#75
0"
1%
1(
#105
0%
0(
1$
1'
#140
1!
1"
1%
1(
