full_adder/fulladd.v
module full_add(a,b,c,carry,sum);
input a,b,c;
output sum,carry;
assign sum=a^b^c;
assign carry=(a&&b)||(b&&c)||(c&&a);
endmodule

full_adder/fulladd_t.v
module fulladd_t;
wire carry,sum;
reg a,b,c;
initial
 begin
 $dumpfile("full_adder.vcd");
 $dumpvars();    
 end
full_add h(a,b,c,carry,sum);
 initial 
        begin 
         #0
         a = 0; b = 0; c=0; 
         #5 
         a = 0; b = 0; c=1;
         #10 
         a = 0; b = 1; c=0;
         #15 
         a = 0; b = 1; c=1;
         #20 
         a = 1; b = 0; c=0;
         #25  
         a = 1; b = 0; c=1;
         #30
         a = 1; b = 1; c=0;
         #35
         a = 1; b = 1; c=1;
        end 
endmodule

full_adder/full_adder.vcd
$date
	Fri May  1 09:33:38 2015
$end
$version
	Icarus Verilog
$end
$timescale
	1s
$end
$scope module fulladd_t $end
$var wire 1 ! carry $end
$var wire 1 " sum $end
$var reg 1 # a $end
$var reg 1 $ b $end
$var reg 1 % c $end
$scope module h $end
$var wire 1 & a $end
$var wire 1 ' b $end
$var wire 1 ( c $end
$var wire 1 ! carry $end
$var wire 1 " sum $end
$upscope $end
$upscope $end
$enddefinitions $end
#0
$dumpvars
0(
0'
0&
0%
0$
0#
0"
0!
$end
#5
1"
1%
1(
#15
0%
0(
1$
1'
#30
1!
0"
1%
1(
#50
0!
1"
0%
0(
0$
0'
1#
1&
#75
1!
0"
1%
1(
#105
0%
0(
1$
1'
#140
1"
1%
1(
